CraftPy/__init__.py
CraftPy/main.py
CraftPy-1.1.2.dist-info/LICENSE.txt
CraftPy-1.1.2.dist-info/METADATA
CraftPy-1.1.2.dist-info/WHEEL
CraftPy-1.1.2.dist-info/top_level.txt
CraftPy-1.1.2.dist-info/RECORD
