Metadata-Version: 2.1
Name: CraftPy
Version: 1.1.2
Summary: Controlling minecraft with python
Home-page: UNKNOWN
Author: Zylops
Author-email: zainaazeez787@gmail.com
License: UNKNOWN
Keywords: python,gaming,mc,control,pyautogui,minecraft
Platform: UNKNOWN
Classifier: Development Status :: 3 - Alpha
Classifier: Intended Audience :: Developers
Classifier: Programming Language :: Python :: 3
Classifier: Operating System :: Unix
Classifier: Operating System :: MacOS :: MacOS X
Classifier: Operating System :: Microsoft :: Windows
Requires-Dist: pyautogui
